ecf/__init__.py
ecf-0.1.dist-info/LICENSE
ecf-0.1.dist-info/METADATA
ecf-0.1.dist-info/WHEEL
ecf-0.1.dist-info/top_level.txt
ecf-0.1.dist-info/RECORD
