Metadata-Version: 2.1
Name: ecf
Version: 0.1
Summary: Empirical Christoffel function for outlier detection
Home-page: https://github.com/PFGimenez/ecf-outlier-detection
Author: Pierre-François Gimenez
Author-email: <pierre-francois.gimenez@laas.fr>
License: UNKNOWN
Platform: UNKNOWN
Classifier: Programming Language :: Python :: 3
Classifier: License :: OSI Approved :: MIT License
Classifier: Operating System :: OS Independent
Requires-Python: >=3.6
